<keymap version="1" name="VSCode (macOS) copy" parent="VSCode OSX">
  <action id="Back">
    <keyboard-shortcut first-keystroke="ctrl minus" />
    <mouse-shortcut keystroke="button4" />
    <keyboard-shortcut first-keystroke="shift ctrl left" />
  </action>
  <action id="CodeCleanup">
    <keyboard-shortcut first-keystroke="shift alt f" />
  </action>
  <action id="CommentByLineComment">
    <keyboard-shortcut first-keystroke="meta k" second-keystroke="meta c" />
    <keyboard-shortcut first-keystroke="meta k" second-keystroke="meta u" />
    <keyboard-shortcut first-keystroke="meta slash" />
    <keyboard-shortcut first-keystroke="ctrl meta 7" />
  </action>
  <action id="Console.TableResult.EditFilterCriteria" />
  <action id="Console.TableResult.NavigateForeignAction">
    <mouse-shortcut keystroke="meta button1" />
    <mouse-shortcut keystroke="Force touch" />
  </action>
  <action id="Console.TableResult.SetDefault" />
  <action id="DatabaseView.FullTextSearch" />
  <action id="Diff.ApplyLeftSide" />
  <action id="Diff.ApplyRightSide" />
  <action id="Diff.FocusOppositePane" />
  <action id="Diff.NextChange" />
  <action id="Diff.PrevChange" />
  <action id="EditorDeleteLine">
    <keyboard-shortcut first-keystroke="shift meta k" />
    <keyboard-shortcut first-keystroke="alt d" />
  </action>
  <action id="EditorDeleteToWordEndInDifferentHumpsMode">
    <keyboard-shortcut first-keystroke="meta alt delete" />
  </action>
  <action id="EditorDeleteToWordStartInDifferentHumpsMode">
    <keyboard-shortcut first-keystroke="meta alt back_space" />
  </action>
  <action id="EditorDuplicate">
    <keyboard-shortcut first-keystroke="shift meta down" />
  </action>
  <action id="EditorNextWordInDifferentHumpsMode">
    <keyboard-shortcut first-keystroke="meta alt right" />
  </action>
  <action id="EditorNextWordInDifferentHumpsModeWithSelection">
    <keyboard-shortcut first-keystroke="shift meta alt right" />
  </action>
  <action id="EditorPasteFromX11" />
  <action id="EditorPreviousWordInDifferentHumpsMode">
    <keyboard-shortcut first-keystroke="meta alt left" />
  </action>
  <action id="EditorPreviousWordInDifferentHumpsModeWithSelection">
    <keyboard-shortcut first-keystroke="shift meta alt left" />
  </action>
  <action id="FindUsages">
    <keyboard-shortcut first-keystroke="alt f7" />
    <keyboard-shortcut first-keystroke="f12" />
  </action>
  <action id="Forward">
    <keyboard-shortcut first-keystroke="shift ctrl minus" />
    <keyboard-shortcut first-keystroke="ctrl meta right" />
    <keyboard-shortcut first-keystroke="shift ctrl right" />
    <mouse-shortcut keystroke="button5" />
  </action>
  <action id="GotoAction">
    <keyboard-shortcut first-keystroke="f1" />
  </action>
  <action id="GotoBookmark0" />
  <action id="GotoBookmark1" />
  <action id="GotoBookmark2" />
  <action id="GotoBookmark3" />
  <action id="GotoBookmark4" />
  <action id="GotoBookmark5" />
  <action id="GotoBookmark6" />
  <action id="GotoBookmark7" />
  <action id="GotoBookmark8" />
  <action id="GotoBookmark9" />
  <action id="GotoDeclaration">
    <mouse-shortcut keystroke="meta button1" />
    <mouse-shortcut keystroke="Force touch" />
  </action>
  <action id="HideSideWindows" />
  <action id="Jdbc.OpenConsole.New" />
  <action id="Jdbc.OpenConsole.New.Generate" />
  <action id="LocateInSolutionView">
    <keyboard-shortcut first-keystroke="ctrl meta l" />
  </action>
  <action id="MethodDown">
    <keyboard-shortcut first-keystroke="meta m" />
  </action>
  <action id="MethodUp">
    <keyboard-shortcut first-keystroke="ctrl meta m" />
  </action>
  <action id="MinimizeCurrentWindow" />
  <action id="MoveElementLeft" />
  <action id="MoveElementRight" />
  <action id="MoveTabRight" />
  <action id="NextEditorTab" />
  <action id="NextTab">
    <keyboard-shortcut first-keystroke="ctrl tab" />
  </action>
  <action id="ParameterInfo.GoToPreviousSignature" />
  <action id="PreviousEditorTab" />
  <action id="PreviousTab">
    <keyboard-shortcut first-keystroke="shift ctrl tab" />
  </action>
  <action id="ReformatCode">
    <keyboard-shortcut first-keystroke="shift meta alt f" />
  </action>
  <action id="Run">
    <keyboard-shortcut first-keystroke="shift meta r" />
  </action>
  <action id="SaveAll">
    <keyboard-shortcut first-keystroke="meta s" />
  </action>
  <action id="SaveDocument" />
  <action id="SearchEverywhere">
    <keyboard-shortcut first-keystroke="shift meta p" />
  </action>
  <action id="SelectAllOccurrences">
    <keyboard-shortcut first-keystroke="meta f2" />
    <keyboard-shortcut first-keystroke="ctrl meta g" />
  </action>
  <action id="ShowContent" />
  <action id="StepOut" />
  <action id="Switcher" />
  <action id="Table-selectFirstRow" />
  <action id="ToggleBookmark">
    <keyboard-shortcut first-keystroke="meta b" />
  </action>
  <action id="Tree-selectFirst" />
  <action id="XDebugger.AttachToProcess">
    <keyboard-shortcut first-keystroke="shift alt f5" />
    <keyboard-shortcut first-keystroke="shift meta a" second-keystroke="d" />
  </action>
  <action id="org.intellij.plugins.markdown.ui.actions.styling.ToggleBoldAction" />
  <action id="org.intellij.plugins.markdown.ui.actions.styling.ToggleStrikethroughAction" />
</keymap>